damv1manipulation/__init__.py
damv1manipulation/mymanipulationstring.py
damv1manipulation-0.0.14.dist-info/METADATA
damv1manipulation-0.0.14.dist-info/WHEEL
damv1manipulation-0.0.14.dist-info/top_level.txt
damv1manipulation-0.0.14.dist-info/RECORD
